setup.py
estimotty/__init__.py
estimotty/estimotty.py
estimotty.egg-info/PKG-INFO
estimotty.egg-info/SOURCES.txt
estimotty.egg-info/dependency_links.txt
estimotty.egg-info/not-zip-safe
estimotty.egg-info/top_level.txt