Metadata-Version: 1.0
Name: estimotty
Version: 0.1.2
Summary: Estimote cloud client
Home-page: https://github.com/OpenInfoporto/python-estimotty.git
Author: Andrea Carmisciano
Author-email: andrea.carmisciano@infoporto.it
License: MIT
Platform: UNKNOWN
